indianfinance/__init__.py
indianfinance/annual_report.py
indianfinance/company.py
indianfinance/utilities/__init__.py
indianfinance/utilities/autocomplete.py
indianfinance/utilities/create_dir.py
indianfinance-0.0.2.dist-info/METADATA
indianfinance-0.0.2.dist-info/WHEEL
indianfinance-0.0.2.dist-info/top_level.txt
indianfinance-0.0.2.dist-info/RECORD
