Metadata-Version: 2.1
Name: indianfinance
Version: 0.0.2
Summary: Indian Financial Markets
Home-page: UNKNOWN
Author: Mrityunjay Samanta
Author-email: samantamrityunjay98@gmail.com
License: UNKNOWN
Keywords: python,financials
Platform: UNKNOWN
Classifier: Development Status :: 3 - Alpha
Classifier: Intended Audience :: Education
Classifier: Programming Language :: Python :: 3
Classifier: Operating System :: MacOS
Classifier: Operating System :: Microsoft :: Windows
Classifier: Operating System :: Unix
Requires-Python: >=3.5
Requires-Dist: requests
